wscreenshot/__init__.py
wscreenshot/wscreenshot.py
wscreenshot-0.0.3.dist-info/LICENSE
wscreenshot-0.0.3.dist-info/METADATA
wscreenshot-0.0.3.dist-info/WHEEL
wscreenshot-0.0.3.dist-info/top_level.txt
wscreenshot-0.0.3.dist-info/RECORD
