Metadata-Version: 2.1
Name: wscreenshot
Version: 0.0.3
Summary: This package which helps you to take screenshot of specific running window
Home-page: https://github.com/saibhaskar24/wscreenshot
Author: saibhaskar
Author-email: saibaaskar24091999@gmail.com
License: MIT License
Platform: UNKNOWN
Classifier: Programming Language :: Python :: 3
Classifier: License :: OSI Approved :: MIT License
Classifier: Operating System :: Microsoft :: Windows
Classifier: Topic :: Multimedia :: Graphics :: Capture :: Screen Capture
Classifier: Topic :: Scientific/Engineering :: Image Processing
Classifier: Environment :: Win32 (MS Windows)
